mistral_common/.DS_Store
mistral_common/__init__.py
mistral_common/audio.py
mistral_common/base.py
mistral_common/exceptions.py
mistral_common/image.py
mistral_common/imports.py
mistral_common/multimodal.py
mistral_common/py.typed
mistral_common/data/mistral_instruct_tokenizer_240216.model.v2
mistral_common/data/mistral_instruct_tokenizer_240323.model.v3
mistral_common/data/mistral_instruct_tokenizer_241114.model.v7
mistral_common/data/mistral_instruct_tokenizer_241114.model.v7m1
mistral_common/data/tekken_240718.json
mistral_common/data/tekken_240911.json
mistral_common/data/tokenizer.model.v1
mistral_common/experimental/__init__.py
mistral_common/experimental/think.py
mistral_common/experimental/tools.py
mistral_common/experimental/utils.py
mistral_common/experimental/app/__init__.py
mistral_common/experimental/app/main.py
mistral_common/experimental/app/models.py
mistral_common/experimental/app/routers.py
mistral_common/integrations/__init__.py
mistral_common/integrations/openai/__init__.py
mistral_common/integrations/openai/pydantic.py
mistral_common/protocol/__init__.py
mistral_common/protocol/base.py
mistral_common/protocol/utils.py
mistral_common/protocol/fim/__init__.py
mistral_common/protocol/fim/request.py
mistral_common/protocol/instruct/__init__.py
mistral_common/protocol/instruct/chunk.py
mistral_common/protocol/instruct/converters.py
mistral_common/protocol/instruct/messages.py
mistral_common/protocol/instruct/normalize.py
mistral_common/protocol/instruct/request.py
mistral_common/protocol/instruct/tool_calls.py
mistral_common/protocol/instruct/validator.py
mistral_common/protocol/transcription/__init__.py
mistral_common/protocol/transcription/request.py
mistral_common/tokens/__init__.py
mistral_common/tokens/instruct/__init__.py
mistral_common/tokens/instruct/request.py
mistral_common/tokens/tokenizers/__init__.py
mistral_common/tokens/tokenizers/audio.py
mistral_common/tokens/tokenizers/base.py
mistral_common/tokens/tokenizers/image.py
mistral_common-1.8.8.dist-info/METADATA
mistral_common-1.8.8.dist-info/WHEEL
mistral_common-1.8.8.dist-info/entry_points.txt
mistral_common-1.8.8.dist-info/top_level.txt
mistral_common-1.8.8.dist-info/RECORD
