Metadata-Version: 2.4
Name: mistral_common
Version: 1.8.8
Summary: Mistral-common is a library of common utilities for Mistral AI.
Author-email: bam4d <bam4d@mistral.ai>
License-Expression: Apache-2.0
Requires-Python: <3.14,>=3.10.0
Requires-Dist: pydantic<3.0,>=2.7
Requires-Dist: jsonschema>=4.21.1
Requires-Dist: typing-extensions>=4.11.0
Requires-Dist: tiktoken>=0.7.0
Requires-Dist: pillow>=10.3.0
Requires-Dist: requests>=2.0.0
Requires-Dist: numpy>=1.25
Requires-Dist: pydantic-extra-types[pycountry]>=2.10.5
Provides-Extra: opencv
Requires-Dist: opencv-python-headless>=4.0.0; extra == "opencv"
Provides-Extra: sentencepiece
Requires-Dist: sentencepiece>=0.2.0; extra == "sentencepiece"
Provides-Extra: soundfile
Requires-Dist: soundfile>=0.12.1; extra == "soundfile"
Provides-Extra: soxr
Requires-Dist: soxr>=0.5.0; extra == "soxr"
Provides-Extra: audio
Requires-Dist: mistral_common[soundfile]; extra == "audio"
Requires-Dist: mistral_common[soxr]; extra == "audio"
Provides-Extra: image
Requires-Dist: mistral_common[opencv]; extra == "image"
Provides-Extra: hf-hub
Requires-Dist: huggingface-hub>=0.32.4; extra == "hf-hub"
Provides-Extra: server
Requires-Dist: fastapi[standard]>=0.115.12; extra == "server"
Requires-Dist: pydantic-settings>=2.9.1; extra == "server"
Requires-Dist: click>=8.1.0; extra == "server"
